D_flip_flop/SR_latch.v
module SR_latch(
	input wire r, input wire s,
	output wire q, output wire nq
);
	assign q = ~(r|nq);
	assign nq = ~(s|q);
endmodule

D_flip_flop/D_latch.v
module D_latch(
	input wire d, input wire e,
	output wire q, output wire nq
);
	wire r;
	wire s;
	assign r = ~d&e;
	assign s = d&e;
	SR_latch SR_latch(r, s, q, nq);
endmodule

D_flip_flop/D_flip_flop.v
module D_flip_flop(
	input wire d, input wire e,
	output wire q, output wire nq
);
	wire w;
	D_latch master(.d(d), .e(!e), .q(w), .nq());
	D_latch slave(.d(w), .e(e), .q(q), .nq(nq));
endmodule

D_flip_flop/testbench.v
`timescale 1ns/100ps
module testbench();

reg clk = 1'b0;
always begin
  #1 clk = ~clk;
end
reg d = 0;
wire q;
D_flip_flop D_flip_flop(.d(d), .e(clk), .q(q), .nq(nq));
initial begin
  $display("start");
  $dumpfile("test.vcd");
  $dumpvars;
  #3 d = 1;
  #2 d = 0;
  #4 d = 1;
  #3 d = 0;
  #4 $finish;
end
endmodule

D_flip_flop/test.vcd
$date
	Wed Feb 24 22:02:30 2021
$end
$version
	Icarus Verilog
$end
$timescale
	100ps
$end
$scope module testbench $end
$var wire 1 ! q $end
$var wire 1 " nq $end
$var reg 1 # clk $end
$var reg 1 $ d $end
$scope module D_flip_flop $end
$var wire 1 $ d $end
$var wire 1 # e $end
$var wire 1 % w $end
$var wire 1 ! q $end
$var wire 1 " nq $end
$scope module master $end
$var wire 1 $ d $end
$var wire 1 & e $end
$var wire 1 ' r $end
$var wire 1 ( s $end
$var wire 1 % q $end
$var wire 1 ) nq $end
$scope module SR_latch $end
$var wire 1 ) nq $end
$var wire 1 % q $end
$var wire 1 ' r $end
$var wire 1 ( s $end
$upscope $end
$upscope $end
$scope module slave $end
$var wire 1 % d $end
$var wire 1 # e $end
$var wire 1 * r $end
$var wire 1 + s $end
$var wire 1 ! q $end
$var wire 1 " nq $end
$scope module SR_latch $end
$var wire 1 " nq $end
$var wire 1 ! q $end
$var wire 1 * r $end
$var wire 1 + s $end
$upscope $end
$upscope $end
$upscope $end
$upscope $end
$enddefinitions $end
#0
$dumpvars
0+
0*
1)
0(
1'
1&
0%
0$
0#
x"
x!
$end
#10
1"
0!
0'
1*
0&
1#
#20
1'
0*
1&
0#
#30
0'
1*
0&
1#
1$
#40
1%
0)
1(
0*
1&
0#
#50
1!
0"
0(
1+
0&
1#
#60
1(
0+
1&
0#
#70
1+
0(
0&
1#
0$
#80
1)
0%
1'
0+
1&
0#
#90
1"
0!
0'
1*
0&
1#
#100
1'
0*
1&
0#
#110
0'
1*
0&
1#
#120
1'
0*
1&
0#
#130
0'
1*
0&
1#
1$
#140
1%
0)
1(
0*
1&
0#
#150
1!
0"
0(
1+
0&
1#
#160
1(
0+
1&
0#
#170
0(
1+
0&
1#
#180
1(
0+
1&
0#
#190
0(
1+
0&
1#
#200
1(
0+
1&
0#
#210
1+
0(
0&
1#
0$
#220
1)
0%
1'
0+
1&
0#
#230
1"
0!
0'
1*
0&
1#
#240
1'
0*
1&
0#
#250
0'
1*
0&
1#
#260
1'
0*
1&
0#
#270
0'
1*
0&
1#
#280
1'
0*
1&
0#
#290
0'
1*
0&
1#
#300
1'
0*
1&
0#
#310
0'
1*
0&
1#
